declxml.py
declxml-1.0.dist-info/METADATA
declxml-1.0.dist-info/RECORD
declxml-1.0.dist-info/WHEEL
declxml-1.0.dist-info/top_level.txt
