Metadata-Version: 2.1
Name: declxml
Version: 1.0
Summary: Declarative XML processing library
Home-page: http://declxml.readthedocs.io/
Author: Greg Atkin
Author-email: greg.scott.atkin@gmail.com
License: MIT
Project-URL: Documentation, http://declxml.readthedocs.io/
Project-URL: Source, https://github.com/gatkin/declxml
Project-URL: Tracker, https://github.com/gatkin/declxml/issues
Keywords: XML,Parsing,Serialization
Platform: UNKNOWN
Classifier: Development Status :: 4 - Beta
Classifier: Intended Audience :: Developers
Classifier: Programming Language :: Python :: 2.7
Classifier: Programming Language :: Python :: 3
Classifier: License :: OSI Approved :: MIT License
